README.rst
pebbletime-cli
pebbletime.py
setup.py
pebbletime.egg-info/PKG-INFO
pebbletime.egg-info/SOURCES.txt
pebbletime.egg-info/dependency_links.txt
pebbletime.egg-info/requires.txt
pebbletime.egg-info/top_level.txt