Metadata-Version: 1.1
Name: pebbletime
Version: 0.1.1
Summary: Module to access the Pebble Timeline API asynchronously
Home-page: https://github.com/aperezdc/pebbletime-python
Author: Adrián Pérez de Castro
Author-email: adrian@perezdecastro.org
License: MIT
Platform: UNKNOWN
Classifier: Development Status :: 3 - Alpha
Classifier: Intended Audience :: Developers
Classifier: Natural Language :: English
Classifier: Programming Language :: Python :: 3.4
Classifier: Programming Language :: Python
Classifier: Operating System :: OS Independent
